[
  {
    "id": "MP24-FR038",
    "cardId": "MP24-FR038",
    "collectionId": "mp24"
  },
  {
    "id": "MP24-FR023",
    "cardId": "MP24-FR023",
    "collectionId": "mp24"
  },
  {
    "id": "MP24-FR045",
    "cardId": "MP24-FR045",
    "collectionId": "mp24"
  },
  {
    "id": "MP24-FR305",
    "cardId": "MP24-FR305",
    "collectionId": "mp24"
  },
  {
    "id": "MP24-FR162",
    "cardId": "MP24-FR162",
    "collectionId": "mp24"
  },
  {
    "id": "MP24-FR061",
    "cardId": "MP24-FR061",
    "collectionId": "mp24"
  },
  {
    "id": "MP24-FR307",
    "cardId": "MP24-FR307",
    "collectionId": "mp24"
  },
  {
    "id": "MP24-FR155",
    "cardId": "MP24-FR155",
    "collectionId": "mp24"
  },
  {
    "id": "MP24-FR020",
    "cardId": "MP24-FR020",
    "collectionId": "mp24"
  },
  {
    "id": "MP24-FR008",
    "cardId": "MP24-FR008",
    "collectionId": "mp24"
  },
  {
    "id": "MP24-FR004",
    "cardId": "MP24-FR004",
    "collectionId": "mp24"
  },
  {
    "id": "MP24-FR005",
    "cardId": "MP24-FR005",
    "collectionId": "mp24"
  },
  {
    "id": "MP24-FR303",
    "cardId": "MP24-FR303",
    "collectionId": "mp24"
  },
  {
    "id": "MP24-FR151",
    "cardId": "MP24-FR151",
    "collectionId": "mp24"
  },
  {
    "id": "MP24-FR011",
    "cardId": "MP24-FR011",
    "collectionId": "mp24"
  },
  {
    "id": "MP24-FR156",
    "cardId": "MP24-FR156",
    "collectionId": "mp24"
  },
  {
    "id": "MP24-FR063",
    "cardId": "MP24-FR063",
    "collectionId": "mp24"
  },
  {
    "id": "MP24-FR160",
    "cardId": "MP24-FR160",
    "collectionId": "mp24"
  },
  {
    "id": "MP24-FR157",
    "cardId": "MP24-FR157",
    "collectionId": "mp24"
  },
  {
    "id": "MP24-FR047",
    "cardId": "MP24-FR047",
    "collectionId": "mp24"
  },
  {
    "id": "MP24-FR306",
    "cardId": "MP24-FR306",
    "collectionId": "mp24"
  },
  {
    "id": "MP24-FR028",
    "cardId": "MP24-FR028",
    "collectionId": "mp24"
  },
  {
    "id": "MP24-FR001",
    "cardId": "MP24-FR001",
    "collectionId": "mp24"
  },
  {
    "id": "MP24-FR029",
    "cardId": "MP24-FR029",
    "collectionId": "mp24"
  },
  {
    "id": "MP24-FR048",
    "cardId": "MP24-FR048",
    "collectionId": "mp24"
  },
  {
    "id": "MP24-FR044",
    "cardId": "MP24-FR044",
    "collectionId": "mp24"
  },
  {
    "id": "MP24-FR024",
    "cardId": "MP24-FR024",
    "collectionId": "mp24"
  },
  {
    "id": "MP24-FR054",
    "cardId": "MP24-FR054",
    "collectionId": "mp24"
  },
  {
    "id": "MP24-FR025",
    "cardId": "MP24-FR025",
    "collectionId": "mp24"
  },
  {
    "id": "MP24-FR163",
    "cardId": "MP24-FR163",
    "collectionId": "mp24"
  },
  {
    "id": "MP24-FR050",
    "cardId": "MP24-FR050",
    "collectionId": "mp24"
  },
  {
    "id": "MP24-FR035",
    "cardId": "MP24-FR035",
    "collectionId": "mp24"
  },
  {
    "id": "MP24-FR161",
    "cardId": "MP24-FR161",
    "collectionId": "mp24"
  },
  {
    "id": "MP24-FR013",
    "cardId": "MP24-FR013",
    "collectionId": "mp24"
  },
  {
    "id": "MP24-FR012",
    "cardId": "MP24-FR012",
    "collectionId": "mp24"
  },
  {
    "id": "MP24-FR014",
    "cardId": "MP24-FR014",
    "collectionId": "mp24"
  },
  {
    "id": "MP24-FR042",
    "cardId": "MP24-FR042",
    "collectionId": "mp24"
  },
  {
    "id": "MP24-FR016",
    "cardId": "MP24-FR016",
    "collectionId": "mp24"
  },
  {
    "id": "MP24-FR158",
    "cardId": "MP24-FR158",
    "collectionId": "mp24"
  },
  {
    "id": "MP24-FR010",
    "cardId": "MP24-FR010",
    "collectionId": "mp24"
  },
  {
    "id": "MP24-FR062",
    "cardId": "MP24-FR062",
    "collectionId": "mp24"
  },
  {
    "id": "MP24-FR147",
    "cardId": "MP24-FR147",
    "collectionId": "mp24"
  },
  {
    "id": "MP24-FR026",
    "cardId": "MP24-FR026",
    "collectionId": "mp24"
  },
  {
    "id": "MP24-FR060",
    "cardId": "MP24-FR060",
    "collectionId": "mp24"
  },
  {
    "id": "MP24-FR002",
    "cardId": "MP24-FR002",
    "collectionId": "mp24"
  },
  {
    "id": "MP24-FR003",
    "cardId": "MP24-FR003",
    "collectionId": "mp24"
  },
  {
    "id": "MP24-FR017",
    "cardId": "MP24-FR017",
    "collectionId": "mp24"
  },
  {
    "id": "MP24-FR058",
    "cardId": "MP24-FR058",
    "collectionId": "mp24"
  },
  {
    "id": "MP24-FR007",
    "cardId": "MP24-FR007",
    "collectionId": "mp24"
  },
  {
    "id": "MP24-FR015",
    "cardId": "MP24-FR015",
    "collectionId": "mp24"
  },
  {
    "id": "MP24-FR039",
    "cardId": "MP24-FR039",
    "collectionId": "mp24"
  },
  {
    "id": "MP24-FR057",
    "cardId": "MP24-FR057",
    "collectionId": "mp24"
  },
  {
    "id": "MP24-FR164",
    "cardId": "MP24-FR164",
    "collectionId": "mp24"
  },
  {
    "id": "MP24-FR009",
    "cardId": "MP24-FR009",
    "collectionId": "mp24"
  },
  {
    "id": "MP24-FR302",
    "cardId": "MP24-FR302",
    "collectionId": "mp24"
  },
  {
    "id": "MP24-FR059",
    "cardId": "MP24-FR059",
    "collectionId": "mp24"
  },
  {
    "id": "MP24-FR032",
    "cardId": "MP24-FR032",
    "collectionId": "mp24"
  },
  {
    "id": "MP24-FR033",
    "cardId": "MP24-FR033",
    "collectionId": "mp24"
  },
  {
    "id": "MP24-FR031",
    "cardId": "MP24-FR031",
    "collectionId": "mp24"
  },
  {
    "id": "MP24-FR037",
    "cardId": "MP24-FR037",
    "collectionId": "mp24"
  },
  {
    "id": "MP24-FR041",
    "cardId": "MP24-FR041",
    "collectionId": "mp24"
  },
  {
    "id": "MP24-FR301",
    "cardId": "MP24-FR301",
    "collectionId": "mp24"
  },
  {
    "id": "MP24-FR019",
    "cardId": "MP24-FR019",
    "collectionId": "mp24"
  },
  {
    "id": "MP24-FR154",
    "cardId": "MP24-FR154",
    "collectionId": "mp24"
  },
  {
    "id": "MP24-FR152",
    "cardId": "MP24-FR152",
    "collectionId": "mp24"
  },
  {
    "id": "MP24-FR056",
    "cardId": "MP24-FR056",
    "collectionId": "mp24"
  },
  {
    "id": "MP24-FR055",
    "cardId": "MP24-FR055",
    "collectionId": "mp24"
  },
  {
    "id": "MP24-FR036",
    "cardId": "MP24-FR036",
    "collectionId": "mp24"
  },
  {
    "id": "MP24-FR131",
    "cardId": "MP24-FR131",
    "collectionId": "mp24"
  },
  {
    "id": "MP24-FR159",
    "cardId": "MP24-FR159",
    "collectionId": "mp24"
  },
  {
    "id": "MP24-FR034",
    "cardId": "MP24-FR034",
    "collectionId": "mp24"
  },
  {
    "id": "MP24-FR006",
    "cardId": "MP24-FR006",
    "collectionId": "mp24"
  },
  {
    "id": "MP24-FR049",
    "cardId": "MP24-FR049",
    "collectionId": "mp24"
  },
  {
    "id": "MP24-FR046",
    "cardId": "MP24-FR046",
    "collectionId": "mp24"
  },
  {
    "id": "MP24-FR022",
    "cardId": "MP24-FR022",
    "collectionId": "mp24"
  },
  {
    "id": "MP24-FR040",
    "cardId": "MP24-FR040",
    "collectionId": "mp24"
  },
  {
    "id": "MP24-FR043",
    "cardId": "MP24-FR043",
    "collectionId": "mp24"
  },
  {
    "id": "MP24-FR027",
    "cardId": "MP24-FR027",
    "collectionId": "mp24"
  },
  {
    "id": "MP24-FR304",
    "cardId": "MP24-FR304",
    "collectionId": "mp24"
  },
  {
    "id": "MP24-FR153",
    "cardId": "MP24-FR153",
    "collectionId": "mp24"
  },
  {
    "id": "MP24-FR021",
    "cardId": "MP24-FR021",
    "collectionId": "mp24"
  }
]